winzy_win_geometry/__init__.py
winzy_win_geometry/_macosgetsize.py
winzy_win_geometry/_wingetsize.py
winzy_win_geometry-0.0.2.dist-info/LICENSE
winzy_win_geometry-0.0.2.dist-info/METADATA
winzy_win_geometry-0.0.2.dist-info/WHEEL
winzy_win_geometry-0.0.2.dist-info/entry_points.txt
winzy_win_geometry-0.0.2.dist-info/top_level.txt
winzy_win_geometry-0.0.2.dist-info/RECORD
