Metadata-Version: 2.1
Name: winzy-win-geometry
Version: 0.0.2
Summary: Get window geometry as a percentage of screen size.
Author: Sukhbinder Singh
License: Apache-2.0
Project-URL: Homepage, https://github.com/sukhbinder/winzy-win-geometry
Project-URL: Changelog, https://github.com/sukhbinder/winzy-win-geometry/releases
Project-URL: Issues, https://github.com/sukhbinder/winzy-win-geometry/issues
Project-URL: CI, https://github.com/sukhbinder/winzy-win-geometry/actions
Classifier: License :: OSI Approved :: Apache Software License
License-File: LICENSE
Requires-Dist: winzy
Requires-Dist: Quartz; sys_platform != "win32"
Provides-Extra: test
Requires-Dist: pytest; extra == "test"
